aibs_informatics_test_resources/__init__.py
aibs_informatics_test_resources/__version__.py
aibs_informatics_test_resources/base.py
aibs_informatics_test_resources/utils.py
aibs_informatics_test_resources-0.1.1.dist-info/METADATA
aibs_informatics_test_resources-0.1.1.dist-info/WHEEL
aibs_informatics_test_resources-0.1.1.dist-info/licenses/LICENSE
aibs_informatics_test_resources-0.1.1.dist-info/RECORD
