Metadata-Version: 2.4
Name: aibs-informatics-test-resources
Version: 0.1.1
Summary: unit test resources for AIBS informatics packages
Project-URL: Documentation, https://.github.io/aibs-informatics-test-resources/
Project-URL: Homepage, https://github.com/AllenInstitute/aibs-informatics-test-resources/
Project-URL: Issues, https://github.com/AllenInstitute/aibs-informatics-test-resources/issues
Project-URL: Repository, https://github.com/AllenInstitute/aibs-informatics-test-resources/
Author-email: AIBS Informatics Group <marmot@alleninstitute.onmicrosoft.com>
Maintainer-email: AIBS Informatics Group <marmot@alleninstitute.onmicrosoft.com>
License: Allen Institute Software License – This software license is the 2-clause BSD 
License-File: LICENSE
Requires-Python: >=3.9
Requires-Dist: coverage[toml]~=7.3
Requires-Dist: pytest-cov
Requires-Dist: pytest~=7.4
Provides-Extra: all
Requires-Dist: black~=23.11.0; extra == 'all'
Requires-Dist: isort~=5.10; extra == 'all'
Requires-Dist: mypy~=1.6; extra == 'all'
Requires-Dist: ruff~=0.9; extra == 'all'
Provides-Extra: linting
Requires-Dist: black~=23.11.0; extra == 'linting'
Requires-Dist: isort~=5.10; extra == 'linting'
Requires-Dist: ruff~=0.9; extra == 'linting'
Provides-Extra: typing
Requires-Dist: mypy~=1.6; extra == 'typing'
